[
  {
    "title": "Save Your Tears (with Ariana Grande) (Remix)",
    "artist": "The Weeknd, Ariana Grande",
    "url": "https://open.spotify.com/track/37BZB0z9T8Xu7U3e65qxFy",
    "albumArt": "https://i.scdn.co/image/ab67616d0000b273c6af5ffa661a365b77df6ef6",
    "playedAt": "2026-01-28T21:12:45.637Z"
  },
  {
    "title": "No Pressure",
    "artist": "KSI",
    "url": "https://open.spotify.com/track/3AoXF9wWBi6IBt7yOoVV2A",
    "albumArt": "https://i.scdn.co/image/ab67616d0000b2734128a48270cd407a81fef739",
    "playedAt": "2026-01-28T20:46:02.969Z"
  },
  {
    "title": "ATM",
    "artist": "Don Toliver",
    "url": "https://open.spotify.com/track/0FrESd7LNffZyGZ37VuSmH",
    "albumArt": "https://i.scdn.co/image/ab67616d0000b2730228270d62beed7dd50c8811",
    "playedAt": "2026-01-28T14:16:36.952Z"
  },
  {
    "title": "Agar Tum Saath Ho (From \"Tamasha\")",
    "artist": "Alka Yagnik, Arijit Singh",
    "url": "https://open.spotify.com/track/6kYoY0PhBelP64UMnhsEZx",
    "albumArt": "https://i.scdn.co/image/ab67616d0000b27325f7621c3c70dd1f868b61bc",
    "playedAt": "2026-01-28T14:12:55.428Z"
  },
  {
    "title": "Kabhi Kabhi Aditi",
    "artist": "Rashid Ali",
    "url": "https://open.spotify.com/track/3APdIdF8H0jsxSuGOqXedS",
    "albumArt": "https://i.scdn.co/image/ab67616d0000b273abf91851997179d195afab5f",
    "playedAt": "2026-01-28T12:41:54.682Z"
  },
  {
    "title": "Humraah (From \"Malang - Unleash The Madness\")",
    "artist": "Sachet Tandon, Kunaal Vermaa, The Fusion Project",
    "url": "https://open.spotify.com/track/4xmkpE1Si5JL7NFxWrhV0S",
    "albumArt": "https://i.scdn.co/image/ab67616d0000b27340494b35d483ac255db4ce93",
    "playedAt": "2026-01-28T12:38:15.103Z"
  },
  {
    "title": "Dil Diyan Gallan",
    "artist": "Atif Aslam",
    "url": "https://open.spotify.com/track/0FBQ4NrrHUbR9kus7rzrOj",
    "albumArt": "https://i.scdn.co/image/ab67616d0000b273f7991610fad937fd9f29f55d",
    "playedAt": "2026-01-28T12:33:14.983Z"
  },
  {
    "title": "Dildaara (Stand By Me)",
    "artist": "Vishal-Shekhar, Shafqat Amanat Ali, Kumaar",
    "url": "https://open.spotify.com/track/6ZoCBDOB308GqUdt2AJrV2",
    "albumArt": "https://i.scdn.co/image/ab67616d0000b27344aa56e23e3a89802e6c6347",
    "playedAt": "2026-01-28T12:28:53.653Z"
  },
  {
    "title": "Kabira",
    "artist": "Pritam, Tochi Raina, Rekha Bhardwaj",
    "url": "https://open.spotify.com/track/4bD9z9qa4qg9BhryvYWB7c",
    "albumArt": "https://i.scdn.co/image/ab67616d0000b273707ea5b8023ac77d31756ed4",
    "playedAt": "2026-01-28T12:24:43.251Z"
  },
  {
    "title": "Boy's a liar Pt. 2",
    "artist": "PinkPantheress, Ice Spice",
    "url": "https://open.spotify.com/track/5CCr8msaN3MhgqBoa9yWhH",
    "albumArt": "https://i.scdn.co/image/ab67616d0000b27312e36c27d935e955b44c6581",
    "playedAt": "2026-01-28T11:15:44.196Z"
  }
]